rustic_ai/api_server/__init__.py
rustic_ai/api_server/addons/__init__.py
rustic_ai/api_server/addons/boards/__init__.py
rustic_ai/api_server/addons/boards/board_store.py
rustic_ai/api_server/addons/boards/models.py
rustic_ai/api_server/addons/boards/router.py
rustic_ai/api_server/addons/boards/schema.py
rustic_ai/api_server/addons/router.py
rustic_ai/api_server/api_dependency_manager.py
rustic_ai/api_server/catalog/__init__.py
rustic_ai/api_server/catalog/catalog_store.py
rustic_ai/api_server/catalog/models.py
rustic_ai/api_server/catalog/router.py
rustic_ai/api_server/guilds/__init__.py
rustic_ai/api_server/guilds/comms_manager.py
rustic_ai/api_server/guilds/models.py
rustic_ai/api_server/guilds/router.py
rustic_ai/api_server/guilds/schema.py
rustic_ai/api_server/guilds/service.py
rustic_ai/api_server/guilds/socket.py
rustic_ai/api_server/guilds/system_comms_manager.py
rustic_ai/api_server/logging/__init__.py
rustic_ai/api_server/logging/config.py
rustic_ai/api_server/logging/format.py
rustic_ai/api_server/main.py
rustic_ai/api_server/main_debug.py
rusticai_api-1.0.0.dist-info/METADATA
rusticai_api-1.0.0.dist-info/WHEEL
rusticai_api-1.0.0.dist-info/RECORD
