Metadata-Version: 2.4
Name: rusticai-api
Version: 1.0.0
Summary: API Server for Rustic AI
License-Expression: Apache-2.0
Author: Dragonscale Industries Inc.
Author-email: dev@dragonscale.ai
Requires-Python: >=3.12,<3.13
Classifier: Programming Language :: Python :: 3
Classifier: Programming Language :: Python :: 3.12
Provides-Extra: test
Requires-Dist: fastapi (>=0.115.8,<0.116.0)
Requires-Dist: griffe (>=1.7.2,<2.0.0)
Requires-Dist: opentelemetry-distro (>=0.52b1,<0.53)
Requires-Dist: psycopg (>=3.2.6,<4.0.0)
Requires-Dist: ptvsd (>=4.3.2,<5.0.0)
Requires-Dist: python-json-logger (>=3.3.0,<4.0.0)
Requires-Dist: python-multipart (>=0.0.20,<0.0.21)
Requires-Dist: rusticai-core (>=1.0.0,<1.1.0)
Requires-Dist: rusticai-ray (>=1.0.0,<1.1.0)
Requires-Dist: starlette (>=0.45.3,<0.46.0)
Requires-Dist: uvicorn (>=0.34.0,<0.35.0)
Requires-Dist: websockets (>=15.0.1,<16.0.0)
Project-URL: Homepage, https://www.rustic.ai/
Project-URL: Repository, https://github.com/rustic-ai/rustic-ai
Project-URL: Rustic AI Core, https://pypi.org/project/rusticai-core/
